{
  "slug": "english-senior2",
  "href": "/knowledge/english-senior2",
  "title": "上海高二英语知识点与学习说明 | 考哪去",
  "description": "整理上海高二英语长阅读、完形、概要写作、翻译和写作表达升级的学习说明。",
  "richBlocks": [
    {
      "type": "element",
      "tag": "div",
      "className": "page-header",
      "children": [
        {
          "type": "element",
          "tag": "h1",
          "children": [
            {
              "type": "text",
              "text": "上海高二英语知识体系与学习说明"
            }
          ]
        },
        {
          "type": "element",
          "tag": "p",
          "children": [
            {
              "type": "text",
              "text": "高二英语要把词汇、语法和篇章理解合成能力。阅读速度、长句处理和表达准确度会直接影响后续高考训练。"
            }
          ]
        },
        {
          "type": "element",
          "tag": "div",
          "className": "page-header-actions",
          "children": [
            {
              "type": "element",
              "tag": "a",
              "href": "#senior2-english-plan",
              "className": "action-link",
              "children": [
                {
                  "type": "text",
                  "text": "查看学习计划"
                }
              ]
            },
            {
              "type": "element",
              "tag": "a",
              "href": "/knowledge/senior-2",
              "className": "action-link",
              "children": [
                {
                  "type": "text",
                  "text": "回到高二总览"
                }
              ]
            }
          ]
        }
      ]
    },
    {
      "type": "element",
      "tag": "section",
      "className": "chapter",
      "children": [
        {
          "type": "element",
          "tag": "h2",
          "children": [
            {
              "type": "text",
              "text": "一、如何使用这份英语资料"
            }
          ]
        },
        {
          "type": "element",
          "tag": "div",
          "className": "important",
          "children": [
            {
              "type": "element",
              "tag": "strong",
              "children": [
                {
                  "type": "text",
                  "text": "学习重点："
                }
              ]
            },
            {
              "type": "text",
              "text": " 高二学习的核心不是提前刷高三压轴，而是把专题知识、题型模型和表达步骤连成稳定链路。每个专题建议按“核心概念 - 典型模型 - 易错条件 - 综合迁移”的顺序整理。 "
            }
          ]
        },
        {
          "type": "element",
          "tag": "div",
          "className": "concept-grid",
          "children": [
            {
              "type": "element",
              "tag": "div",
              "className": "concept-card",
              "children": [
                {
                  "type": "element",
                  "tag": "h4",
                  "children": [
                    {
                      "type": "text",
                      "text": "关键点"
                    }
                  ]
                },
                {
                  "type": "element",
                  "tag": "p",
                  "children": [
                    {
                      "type": "text",
                      "text": "词汇不只背中文义，要同步积累搭配、语域、派生和句中功能。"
                    }
                  ]
                }
              ]
            },
            {
              "type": "element",
              "tag": "div",
              "className": "concept-card",
              "children": [
                {
                  "type": "element",
                  "tag": "h4",
                  "children": [
                    {
                      "type": "text",
                      "text": "常考方向"
                    }
                  ]
                },
                {
                  "type": "element",
                  "tag": "p",
                  "children": [
                    {
                      "type": "text",
                      "text": "长阅读、完形、概要、翻译、应用文和开放性写作。"
                    }
                  ]
                }
              ]
            },
            {
              "type": "element",
              "tag": "div",
              "className": "concept-card",
              "children": [
                {
                  "type": "element",
                  "tag": "h4",
                  "children": [
                    {
                      "type": "text",
                      "text": "复习提醒"
                    }
                  ]
                },
                {
                  "type": "element",
                  "tag": "p",
                  "children": [
                    {
                      "type": "text",
                      "text": "高二应开始固定输出，避免阅读能懂但翻译和写作写不出来。"
                    }
                  ]
                }
              ]
            }
          ]
        },
        {
          "type": "element",
          "tag": "p",
          "children": [
            {
              "type": "text",
              "text": "如果是选科科目，建议把本页当作阶段复盘清单：先补概念断点，再练中档综合题，最后整理能迁移到高三一轮复习的模型卡片。"
            }
          ]
        }
      ]
    },
    {
      "type": "element",
      "tag": "section",
      "className": "chapter",
      "id": "senior2-english-reading-cloze",
      "children": [
        {
          "type": "element",
          "tag": "h2",
          "children": [
            {
              "type": "text",
              "text": "二、长阅读与完形"
            }
          ]
        },
        {
          "type": "element",
          "tag": "p",
          "children": [
            {
              "type": "text",
              "text": "阅读训练的重点是理解篇章结构，而不是逐词翻译。"
            }
          ]
        },
        {
          "type": "element",
          "tag": "h3",
          "children": [
            {
              "type": "text",
              "text": "核心知识"
            }
          ]
        },
        {
          "type": "element",
          "tag": "ul",
          "children": [
            {
              "type": "element",
              "tag": "li",
              "children": [
                {
                  "type": "text",
                  "text": "先判断文章类型、段落功能和作者态度。"
                }
              ]
            },
            {
              "type": "element",
              "tag": "li",
              "children": [
                {
                  "type": "text",
                  "text": "长难句先找主干，再补充从句、非谓语和修饰成分。"
                }
              ]
            },
            {
              "type": "element",
              "tag": "li",
              "children": [
                {
                  "type": "text",
                  "text": "完形要结合上下文逻辑、词义辨析和固定搭配。"
                }
              ]
            }
          ]
        },
        {
          "type": "element",
          "tag": "div",
          "className": "concept-grid",
          "children": [
            {
              "type": "element",
              "tag": "div",
              "className": "concept-card",
              "children": [
                {
                  "type": "element",
                  "tag": "h4",
                  "children": [
                    {
                      "type": "text",
                      "text": "模型"
                    }
                  ]
                },
                {
                  "type": "element",
                  "tag": "p",
                  "children": [
                    {
                      "type": "text",
                      "text": "题干定位 - 段落功能 - 选项比对 - 回文验证。"
                    }
                  ]
                }
              ]
            },
            {
              "type": "element",
              "tag": "div",
              "className": "concept-card",
              "children": [
                {
                  "type": "element",
                  "tag": "h4",
                  "children": [
                    {
                      "type": "text",
                      "text": "易错点"
                    }
                  ]
                },
                {
                  "type": "element",
                  "tag": "p",
                  "children": [
                    {
                      "type": "text",
                      "text": "只凭单词熟悉度选答案，不看语境和篇章逻辑。"
                    }
                  ]
                }
              ]
            }
          ]
        },
        {
          "type": "element",
          "tag": "div",
          "className": "important",
          "children": [
            {
              "type": "element",
              "tag": "strong",
              "children": [
                {
                  "type": "text",
                  "text": "例题训练："
                }
              ]
            },
            {
              "type": "text",
              "text": " 每篇阅读做完后，用 3 句话写出文章结构和作者立场。 "
            }
          ]
        }
      ]
    },
    {
      "type": "element",
      "tag": "section",
      "className": "chapter",
      "id": "senior2-english-summary-translation",
      "children": [
        {
          "type": "element",
          "tag": "h2",
          "children": [
            {
              "type": "text",
              "text": "三、概要写作与翻译"
            }
          ]
        },
        {
          "type": "element",
          "tag": "p",
          "children": [
            {
              "type": "text",
              "text": "概要和翻译最能暴露语言组织能力，需要持续小步训练。"
            }
          ]
        },
        {
          "type": "element",
          "tag": "h3",
          "children": [
            {
              "type": "text",
              "text": "核心知识"
            }
          ]
        },
        {
          "type": "element",
          "tag": "ul",
          "children": [
            {
              "type": "element",
              "tag": "li",
              "children": [
                {
                  "type": "text",
                  "text": "概要写作先抓主旨、要点和逻辑连接。"
                }
              ]
            },
            {
              "type": "element",
              "tag": "li",
              "children": [
                {
                  "type": "text",
                  "text": "翻译题重视句型选择、时态语态和中文信息重组。"
                }
              ]
            },
            {
              "type": "element",
              "tag": "li",
              "children": [
                {
                  "type": "text",
                  "text": "积累常用表达时要记录适用语境。"
                }
              ]
            }
          ]
        },
        {
          "type": "element",
          "tag": "div",
          "className": "concept-grid",
          "children": [
            {
              "type": "element",
              "tag": "div",
              "className": "concept-card",
              "children": [
                {
                  "type": "element",
                  "tag": "h4",
                  "children": [
                    {
                      "type": "text",
                      "text": "模型"
                    }
                  ]
                },
                {
                  "type": "element",
                  "tag": "p",
                  "children": [
                    {
                      "type": "text",
                      "text": "提炼主干 - 合并要点 - 控制字数 - 检查语法。"
                    }
                  ]
                }
              ]
            },
            {
              "type": "element",
              "tag": "div",
              "className": "concept-card",
              "children": [
                {
                  "type": "element",
                  "tag": "h4",
                  "children": [
                    {
                      "type": "text",
                      "text": "易错点"
                    }
                  ]
                },
                {
                  "type": "element",
                  "tag": "p",
                  "children": [
                    {
                      "type": "text",
                      "text": "概要变成照抄原句，翻译只按中文顺序硬译。"
                    }
                  ]
                }
              ]
            }
          ]
        },
        {
          "type": "element",
          "tag": "div",
          "className": "important",
          "children": [
            {
              "type": "element",
              "tag": "strong",
              "children": [
                {
                  "type": "text",
                  "text": "例题训练："
                }
              ]
            },
            {
              "type": "text",
              "text": " 每周完成 3 个翻译句和 1 篇概要，重点修改动词和连接词。 "
            }
          ]
        }
      ]
    },
    {
      "type": "element",
      "tag": "section",
      "className": "chapter",
      "id": "senior2-english-writing",
      "children": [
        {
          "type": "element",
          "tag": "h2",
          "children": [
            {
              "type": "text",
              "text": "四、写作表达升级"
            }
          ]
        },
        {
          "type": "element",
          "tag": "p",
          "children": [
            {
              "type": "text",
              "text": "高二写作要从“句子正确”升级到“结构清楚、表达自然”。"
            }
          ]
        },
        {
          "type": "element",
          "tag": "h3",
          "children": [
            {
              "type": "text",
              "text": "核心知识"
            }
          ]
        },
        {
          "type": "element",
          "tag": "ul",
          "children": [
            {
              "type": "element",
              "tag": "li",
              "children": [
                {
                  "type": "text",
                  "text": "常备开头、承接、举例、转折和总结表达。"
                }
              ]
            },
            {
              "type": "element",
              "tag": "li",
              "children": [
                {
                  "type": "text",
                  "text": "主体段落保持主题句、解释句和例证句完整。"
                }
              ]
            },
            {
              "type": "element",
              "tag": "li",
              "children": [
                {
                  "type": "text",
                  "text": "修改作文时优先检查动词、从句、连接词和名词搭配。"
                }
              ]
            }
          ]
        },
        {
          "type": "element",
          "tag": "div",
          "className": "concept-grid",
          "children": [
            {
              "type": "element",
              "tag": "div",
              "className": "concept-card",
              "children": [
                {
                  "type": "element",
                  "tag": "h4",
                  "children": [
                    {
                      "type": "text",
                      "text": "模型"
                    }
                  ]
                },
                {
                  "type": "element",
                  "tag": "p",
                  "children": [
                    {
                      "type": "text",
                      "text": "审题对象 - 写作目的 - 段落功能 - 语言润色。"
                    }
                  ]
                }
              ]
            },
            {
              "type": "element",
              "tag": "div",
              "className": "concept-card",
              "children": [
                {
                  "type": "element",
                  "tag": "h4",
                  "children": [
                    {
                      "type": "text",
                      "text": "易错点"
                    }
                  ]
                },
                {
                  "type": "element",
                  "tag": "p",
                  "children": [
                    {
                      "type": "text",
                      "text": "追求复杂句导致语法错误，或全文缺少清晰推进。"
                    }
                  ]
                }
              ]
            }
          ]
        },
        {
          "type": "element",
          "tag": "div",
          "className": "important",
          "children": [
            {
              "type": "element",
              "tag": "strong",
              "children": [
                {
                  "type": "text",
                  "text": "例题训练："
                }
              ]
            },
            {
              "type": "text",
              "text": " 把一篇作文改写两版：一版追求准确，一版追求表达丰富。 "
            }
          ]
        }
      ]
    },
    {
      "type": "element",
      "tag": "section",
      "className": "chapter",
      "id": "senior2-english-plan",
      "children": [
        {
          "type": "element",
          "tag": "h2",
          "children": [
            {
              "type": "text",
              "text": "五、高二英语阶段提升计划"
            }
          ]
        },
        {
          "type": "element",
          "tag": "p",
          "children": [
            {
              "type": "text",
              "text": "建议每天小剂量输入输出，形成稳定语言手感。"
            }
          ]
        },
        {
          "type": "element",
          "tag": "div",
          "className": "concept-grid",
          "children": [
            {
              "type": "element",
              "tag": "div",
              "className": "concept-card",
              "children": [
                {
                  "type": "element",
                  "tag": "h4",
                  "children": [
                    {
                      "type": "text",
                      "text": "词汇"
                    }
                  ]
                },
                {
                  "type": "element",
                  "tag": "p",
                  "children": [
                    {
                      "type": "text",
                      "text": "每天 20 个核心词，记录搭配和例句。"
                    }
                  ]
                }
              ]
            },
            {
              "type": "element",
              "tag": "div",
              "className": "concept-card",
              "children": [
                {
                  "type": "element",
                  "tag": "h4",
                  "children": [
                    {
                      "type": "text",
                      "text": "阅读"
                    }
                  ]
                },
                {
                  "type": "element",
                  "tag": "p",
                  "children": [
                    {
                      "type": "text",
                      "text": "每周 3 篇精读，关注结构和长句。"
                    }
                  ]
                }
              ]
            },
            {
              "type": "element",
              "tag": "div",
              "className": "concept-card",
              "children": [
                {
                  "type": "element",
                  "tag": "h4",
                  "children": [
                    {
                      "type": "text",
                      "text": "输出"
                    }
                  ]
                },
                {
                  "type": "element",
                  "tag": "p",
                  "children": [
                    {
                      "type": "text",
                      "text": "每周 2 组翻译、1 篇概要、1 段作文改写。"
                    }
                  ]
                }
              ]
            }
          ]
        },
        {
          "type": "element",
          "tag": "table",
          "children": [
            {
              "type": "element",
              "tag": "thead",
              "children": [
                {
                  "type": "element",
                  "tag": "tr",
                  "children": [
                    {
                      "type": "element",
                      "tag": "th",
                      "children": [
                        {
                          "type": "text",
                          "text": "阶段"
                        }
                      ]
                    },
                    {
                      "type": "element",
                      "tag": "th",
                      "children": [
                        {
                          "type": "text",
                          "text": "主要任务"
                        }
                      ]
                    },
                    {
                      "type": "element",
                      "tag": "th",
                      "children": [
                        {
                          "type": "text",
                          "text": "完成标志"
                        }
                      ]
                    }
                  ]
                }
              ]
            },
            {
              "type": "element",
              "tag": "tbody",
              "children": [
                {
                  "type": "element",
                  "tag": "tr",
                  "children": [
                    {
                      "type": "element",
                      "tag": "td",
                      "children": [
                        {
                          "type": "text",
                          "text": "第 1 阶段"
                        }
                      ]
                    },
                    {
                      "type": "element",
                      "tag": "td",
                      "children": [
                        {
                          "type": "text",
                          "text": "补词汇搭配和长句主干"
                        }
                      ]
                    },
                    {
                      "type": "element",
                      "tag": "td",
                      "children": [
                        {
                          "type": "text",
                          "text": "阅读定位更快，错因可归类"
                        }
                      ]
                    }
                  ]
                },
                {
                  "type": "element",
                  "tag": "tr",
                  "children": [
                    {
                      "type": "element",
                      "tag": "td",
                      "children": [
                        {
                          "type": "text",
                          "text": "第 2 阶段"
                        }
                      ]
                    },
                    {
                      "type": "element",
                      "tag": "td",
                      "children": [
                        {
                          "type": "text",
                          "text": "训练概要、翻译和完形逻辑"
                        }
                      ]
                    },
                    {
                      "type": "element",
                      "tag": "td",
                      "children": [
                        {
                          "type": "text",
                          "text": "表达不再严重依赖中文顺序"
                        }
                      ]
                    }
                  ]
                },
                {
                  "type": "element",
                  "tag": "tr",
                  "children": [
                    {
                      "type": "element",
                      "tag": "td",
                      "children": [
                        {
                          "type": "text",
                          "text": "第 3 阶段"
                        }
                      ]
                    },
                    {
                      "type": "element",
                      "tag": "td",
                      "children": [
                        {
                          "type": "text",
                          "text": "稳定写作结构和语言库"
                        }
                      ]
                    },
                    {
                      "type": "element",
                      "tag": "td",
                      "children": [
                        {
                          "type": "text",
                          "text": "能在限时内完成清楚准确的输出"
                        }
                      ]
                    }
                  ]
                }
              ]
            }
          ]
        }
      ]
    }
  ],
  "sourceFiles": [
    "data/knowledge-pages.json"
  ]
}