{
  "slug": "physics-senior2",
  "href": "/knowledge/physics-senior2",
  "title": "上海高二物理知识点 | 静电场/恒定电流/磁场/电磁感应 | 考哪去",
  "description": "依据沪科版高二物理教材整合电磁学核心内容。",
  "richBlocks": [
    {
      "type": "element",
      "tag": "div",
      "className": "page-header",
      "children": [
        {
          "type": "element",
          "tag": "h1",
          "children": [
            {
              "type": "text",
              "text": "上海高二物理知识体系与学习说明"
            }
          ]
        },
        {
          "type": "element",
          "tag": "p",
          "children": [
            {
              "type": "text",
              "text": "高二物理从力学主线进入电磁学主线，抽象程度更高。要把场、能量、图像和实验误差连成同一套分析语言。"
            }
          ]
        },
        {
          "type": "element",
          "tag": "div",
          "className": "page-header-actions",
          "children": [
            {
              "type": "element",
              "tag": "a",
              "href": "#senior2-physics-plan",
              "className": "action-link",
              "children": [
                {
                  "type": "text",
                  "text": "查看学习计划"
                }
              ]
            },
            {
              "type": "element",
              "tag": "a",
              "href": "/knowledge/senior-2",
              "className": "action-link",
              "children": [
                {
                  "type": "text",
                  "text": "回到高二总览"
                }
              ]
            }
          ]
        }
      ]
    },
    {
      "type": "element",
      "tag": "section",
      "className": "chapter",
      "children": [
        {
          "type": "element",
          "tag": "h2",
          "children": [
            {
              "type": "text",
              "text": "一、如何使用这份物理资料"
            }
          ]
        },
        {
          "type": "element",
          "tag": "div",
          "className": "important",
          "children": [
            {
              "type": "element",
              "tag": "strong",
              "children": [
                {
                  "type": "text",
                  "text": "学习重点："
                }
              ]
            },
            {
              "type": "text",
              "text": " 高二学习的核心不是提前刷高三压轴，而是把专题知识、题型模型和表达步骤连成稳定链路。每个专题建议按“核心概念 - 典型模型 - 易错条件 - 综合迁移”的顺序整理。 "
            }
          ]
        },
        {
          "type": "element",
          "tag": "div",
          "className": "concept-grid",
          "children": [
            {
              "type": "element",
              "tag": "div",
              "className": "concept-card",
              "children": [
                {
                  "type": "element",
                  "tag": "h4",
                  "children": [
                    {
                      "type": "text",
                      "text": "关键点"
                    }
                  ]
                },
                {
                  "type": "element",
                  "tag": "p",
                  "children": [
                    {
                      "type": "text",
                      "text": "用“对象 - 过程 - 规律 - 图像 - 能量”五步分析电磁学问题。"
                    }
                  ]
                }
              ]
            },
            {
              "type": "element",
              "tag": "div",
              "className": "concept-card",
              "children": [
                {
                  "type": "element",
                  "tag": "h4",
                  "children": [
                    {
                      "type": "text",
                      "text": "常考方向"
                    }
                  ]
                },
                {
                  "type": "element",
                  "tag": "p",
                  "children": [
                    {
                      "type": "text",
                      "text": "电场、电势、电路、磁场、带电粒子、感应前置和实验数据处理。"
                    }
                  ]
                }
              ]
            },
            {
              "type": "element",
              "tag": "div",
              "className": "concept-card",
              "children": [
                {
                  "type": "element",
                  "tag": "h4",
                  "children": [
                    {
                      "type": "text",
                      "text": "复习提醒"
                    }
                  ]
                },
                {
                  "type": "element",
                  "tag": "p",
                  "children": [
                    {
                      "type": "text",
                      "text": "电磁学不能只背公式，必须画图并说明方向、正负号和适用条件。"
                    }
                  ]
                }
              ]
            }
          ]
        },
        {
          "type": "element",
          "tag": "p",
          "children": [
            {
              "type": "text",
              "text": "如果是选科科目，建议把本页当作阶段复盘清单：先补概念断点，再练中档综合题，最后整理能迁移到高三一轮复习的模型卡片。"
            }
          ]
        }
      ]
    },
    {
      "type": "element",
      "tag": "section",
      "className": "chapter",
      "id": "senior2-physics-electric-field",
      "children": [
        {
          "type": "element",
          "tag": "h2",
          "children": [
            {
              "type": "text",
              "text": "二、电场、电势与电路模型"
            }
          ]
        },
        {
          "type": "element",
          "tag": "p",
          "children": [
            {
              "type": "text",
              "text": "电学的第一关是把抽象场量和具体电路量区分清楚。"
            }
          ]
        },
        {
          "type": "element",
          "tag": "h3",
          "children": [
            {
              "type": "text",
              "text": "核心知识"
            }
          ]
        },
        {
          "type": "element",
          "tag": "ul",
          "children": [
            {
              "type": "element",
              "tag": "li",
              "children": [
                {
                  "type": "text",
                  "text": "理解电场强度、电势、电势能、电压之间的关系。"
                }
              ]
            },
            {
              "type": "element",
              "tag": "li",
              "children": [
                {
                  "type": "text",
                  "text": "电路题先判断串并联、等效电路和电表影响。"
                }
              ]
            },
            {
              "type": "element",
              "tag": "li",
              "children": [
                {
                  "type": "text",
                  "text": "会用能量观点处理带电粒子在电场中的运动。"
                }
              ]
            }
          ]
        },
        {
          "type": "element",
          "tag": "div",
          "className": "concept-grid",
          "children": [
            {
              "type": "element",
              "tag": "div",
              "className": "concept-card",
              "children": [
                {
                  "type": "element",
                  "tag": "h4",
                  "children": [
                    {
                      "type": "text",
                      "text": "模型"
                    }
                  ]
                },
                {
                  "type": "element",
                  "tag": "p",
                  "children": [
                    {
                      "type": "text",
                      "text": "受力方向 - 电势变化 - 能量转化 - 运动结果。"
                    }
                  ]
                }
              ]
            },
            {
              "type": "element",
              "tag": "div",
              "className": "concept-card",
              "children": [
                {
                  "type": "element",
                  "tag": "h4",
                  "children": [
                    {
                      "type": "text",
                      "text": "易错点"
                    }
                  ]
                },
                {
                  "type": "element",
                  "tag": "p",
                  "children": [
                    {
                      "type": "text",
                      "text": "混淆电场线方向、电势高低和电荷正负。"
                    }
                  ]
                }
              ]
            }
          ]
        },
        {
          "type": "element",
          "tag": "div",
          "className": "important",
          "children": [
            {
              "type": "element",
              "tag": "strong",
              "children": [
                {
                  "type": "text",
                  "text": "例题训练："
                }
              ]
            },
            {
              "type": "text",
              "text": " 每道电场题都画出电场线、受力方向和能量变化表。 "
            }
          ]
        }
      ]
    },
    {
      "type": "element",
      "tag": "section",
      "className": "chapter",
      "id": "senior2-physics-magnetism",
      "children": [
        {
          "type": "element",
          "tag": "h2",
          "children": [
            {
              "type": "text",
              "text": "三、磁场与电磁感应前置"
            }
          ]
        },
        {
          "type": "element",
          "tag": "p",
          "children": [
            {
              "type": "text",
              "text": "磁场题重在方向判断和运动过程分析，是高二后段的重要综合点。"
            }
          ]
        },
        {
          "type": "element",
          "tag": "h3",
          "children": [
            {
              "type": "text",
              "text": "核心知识"
            }
          ]
        },
        {
          "type": "element",
          "tag": "ul",
          "children": [
            {
              "type": "element",
              "tag": "li",
              "children": [
                {
                  "type": "text",
                  "text": "掌握左手定则、右手定则和感应电流方向判断。"
                }
              ]
            },
            {
              "type": "element",
              "tag": "li",
              "children": [
                {
                  "type": "text",
                  "text": "带电粒子在磁场中运动要找圆心、半径和周期。"
                }
              ]
            },
            {
              "type": "element",
              "tag": "li",
              "children": [
                {
                  "type": "text",
                  "text": "电磁感应题先判断磁通量变化，再判断电流和受力。"
                }
              ]
            }
          ]
        },
        {
          "type": "element",
          "tag": "div",
          "className": "concept-grid",
          "children": [
            {
              "type": "element",
              "tag": "div",
              "className": "concept-card",
              "children": [
                {
                  "type": "element",
                  "tag": "h4",
                  "children": [
                    {
                      "type": "text",
                      "text": "模型"
                    }
                  ]
                },
                {
                  "type": "element",
                  "tag": "p",
                  "children": [
                    {
                      "type": "text",
                      "text": "区域图 - 方向判断 - 几何关系 - 动力学/能量。"
                    }
                  ]
                }
              ]
            },
            {
              "type": "element",
              "tag": "div",
              "className": "concept-card",
              "children": [
                {
                  "type": "element",
                  "tag": "h4",
                  "children": [
                    {
                      "type": "text",
                      "text": "易错点"
                    }
                  ]
                },
                {
                  "type": "element",
                  "tag": "p",
                  "children": [
                    {
                      "type": "text",
                      "text": "方向定则混用，或忽略粒子速度方向与磁场方向关系。"
                    }
                  ]
                }
              ]
            }
          ]
        },
        {
          "type": "element",
          "tag": "div",
          "className": "important",
          "children": [
            {
              "type": "element",
              "tag": "strong",
              "children": [
                {
                  "type": "text",
                  "text": "例题训练："
                }
              ]
            },
            {
              "type": "text",
              "text": " 整理一页方向判断清单，配 6 个典型示意图反复复盘。 "
            }
          ]
        }
      ]
    },
    {
      "type": "element",
      "tag": "section",
      "className": "chapter",
      "id": "senior2-physics-experiment",
      "children": [
        {
          "type": "element",
          "tag": "h2",
          "children": [
            {
              "type": "text",
              "text": "四、实验、图像与综合题"
            }
          ]
        },
        {
          "type": "element",
          "tag": "p",
          "children": [
            {
              "type": "text",
              "text": "高二物理实验更强调图像斜率、截距和误差来源的解释。"
            }
          ]
        },
        {
          "type": "element",
          "tag": "h3",
          "children": [
            {
              "type": "text",
              "text": "核心知识"
            }
          ]
        },
        {
          "type": "element",
          "tag": "ul",
          "children": [
            {
              "type": "element",
              "tag": "li",
              "children": [
                {
                  "type": "text",
                  "text": "会把实验数据转化为图像并解释物理意义。"
                }
              ]
            },
            {
              "type": "element",
              "tag": "li",
              "children": [
                {
                  "type": "text",
                  "text": "理解仪器读数、有效数字和系统误差。"
                }
              ]
            },
            {
              "type": "element",
              "tag": "li",
              "children": [
                {
                  "type": "text",
                  "text": "综合题中明确每一段过程适用的物理规律。"
                }
              ]
            }
          ]
        },
        {
          "type": "element",
          "tag": "div",
          "className": "concept-grid",
          "children": [
            {
              "type": "element",
              "tag": "div",
              "className": "concept-card",
              "children": [
                {
                  "type": "element",
                  "tag": "h4",
                  "children": [
                    {
                      "type": "text",
                      "text": "模型"
                    }
                  ]
                },
                {
                  "type": "element",
                  "tag": "p",
                  "children": [
                    {
                      "type": "text",
                      "text": "实验目的 - 控制变量 - 数据处理 - 误差分析。"
                    }
                  ]
                }
              ]
            },
            {
              "type": "element",
              "tag": "div",
              "className": "concept-card",
              "children": [
                {
                  "type": "element",
                  "tag": "h4",
                  "children": [
                    {
                      "type": "text",
                      "text": "易错点"
                    }
                  ]
                },
                {
                  "type": "element",
                  "tag": "p",
                  "children": [
                    {
                      "type": "text",
                      "text": "只代公式，不说明图像斜率或截距代表什么。"
                    }
                  ]
                }
              ]
            }
          ]
        },
        {
          "type": "element",
          "tag": "div",
          "className": "important",
          "children": [
            {
              "type": "element",
              "tag": "strong",
              "children": [
                {
                  "type": "text",
                  "text": "例题训练："
                }
              ]
            },
            {
              "type": "text",
              "text": " 每周复盘 1 个电学实验，写出电路图、数据表和误差说明。 "
            }
          ]
        }
      ]
    },
    {
      "type": "element",
      "tag": "section",
      "className": "chapter",
      "id": "senior2-physics-plan",
      "children": [
        {
          "type": "element",
          "tag": "h2",
          "children": [
            {
              "type": "text",
              "text": "五、高二物理阶段提升计划"
            }
          ]
        },
        {
          "type": "element",
          "tag": "p",
          "children": [
            {
              "type": "text",
              "text": "建议把电磁学和实验图像同步推进，避免公式孤岛。"
            }
          ]
        },
        {
          "type": "element",
          "tag": "div",
          "className": "concept-grid",
          "children": [
            {
              "type": "element",
              "tag": "div",
              "className": "concept-card",
              "children": [
                {
                  "type": "element",
                  "tag": "h4",
                  "children": [
                    {
                      "type": "text",
                      "text": "概念线"
                    }
                  ]
                },
                {
                  "type": "element",
                  "tag": "p",
                  "children": [
                    {
                      "type": "text",
                      "text": "场、电势、磁通量等概念要配图记忆。"
                    }
                  ]
                }
              ]
            },
            {
              "type": "element",
              "tag": "div",
              "className": "concept-card",
              "children": [
                {
                  "type": "element",
                  "tag": "h4",
                  "children": [
                    {
                      "type": "text",
                      "text": "模型线"
                    }
                  ]
                },
                {
                  "type": "element",
                  "tag": "p",
                  "children": [
                    {
                      "type": "text",
                      "text": "带电粒子、电路等效和感应过程各建模型卡。"
                    }
                  ]
                }
              ]
            },
            {
              "type": "element",
              "tag": "div",
              "className": "concept-card",
              "children": [
                {
                  "type": "element",
                  "tag": "h4",
                  "children": [
                    {
                      "type": "text",
                      "text": "实验线"
                    }
                  ]
                },
                {
                  "type": "element",
                  "tag": "p",
                  "children": [
                    {
                      "type": "text",
                      "text": "每个实验保留原理、图像和误差三栏。"
                    }
                  ]
                }
              ]
            }
          ]
        },
        {
          "type": "element",
          "tag": "table",
          "children": [
            {
              "type": "element",
              "tag": "thead",
              "children": [
                {
                  "type": "element",
                  "tag": "tr",
                  "children": [
                    {
                      "type": "element",
                      "tag": "th",
                      "children": [
                        {
                          "type": "text",
                          "text": "阶段"
                        }
                      ]
                    },
                    {
                      "type": "element",
                      "tag": "th",
                      "children": [
                        {
                          "type": "text",
                          "text": "主要任务"
                        }
                      ]
                    },
                    {
                      "type": "element",
                      "tag": "th",
                      "children": [
                        {
                          "type": "text",
                          "text": "完成标志"
                        }
                      ]
                    }
                  ]
                }
              ]
            },
            {
              "type": "element",
              "tag": "tbody",
              "children": [
                {
                  "type": "element",
                  "tag": "tr",
                  "children": [
                    {
                      "type": "element",
                      "tag": "td",
                      "children": [
                        {
                          "type": "text",
                          "text": "第 1 阶段"
                        }
                      ]
                    },
                    {
                      "type": "element",
                      "tag": "td",
                      "children": [
                        {
                          "type": "text",
                          "text": "补电场和电路基础模型"
                        }
                      ]
                    },
                    {
                      "type": "element",
                      "tag": "td",
                      "children": [
                        {
                          "type": "text",
                          "text": "能准确画图并判断方向"
                        }
                      ]
                    }
                  ]
                },
                {
                  "type": "element",
                  "tag": "tr",
                  "children": [
                    {
                      "type": "element",
                      "tag": "td",
                      "children": [
                        {
                          "type": "text",
                          "text": "第 2 阶段"
                        }
                      ]
                    },
                    {
                      "type": "element",
                      "tag": "td",
                      "children": [
                        {
                          "type": "text",
                          "text": "训练磁场和感应前置"
                        }
                      ]
                    },
                    {
                      "type": "element",
                      "tag": "td",
                      "children": [
                        {
                          "type": "text",
                          "text": "过程分析不再只靠套公式"
                        }
                      ]
                    }
                  ]
                },
                {
                  "type": "element",
                  "tag": "tr",
                  "children": [
                    {
                      "type": "element",
                      "tag": "td",
                      "children": [
                        {
                          "type": "text",
                          "text": "第 3 阶段"
                        }
                      ]
                    },
                    {
                      "type": "element",
                      "tag": "td",
                      "children": [
                        {
                          "type": "text",
                          "text": "整合实验与综合题"
                        }
                      ]
                    },
                    {
                      "type": "element",
                      "tag": "td",
                      "children": [
                        {
                          "type": "text",
                          "text": "能解释图像、误差和规律适用条件"
                        }
                      ]
                    }
                  ]
                }
              ]
            }
          ]
        }
      ]
    },
    {
      "type": "element",
      "tag": "h2",
      "className": "section-title",
      "children": [
        {
          "type": "text",
          "text": "静电场"
        }
      ]
    },
    {
      "type": "element",
      "tag": "p",
      "children": [
        {
          "type": "text",
          "text": "电荷守恒定律库仑定律。电场强度电势电势差电势能。电容器的电容和平行板电容器。"
        }
      ]
    },
    {
      "type": "element",
      "tag": "h2",
      "className": "section-title",
      "children": [
        {
          "type": "text",
          "text": "恒定电流"
        }
      ]
    },
    {
      "type": "element",
      "tag": "p",
      "children": [
        {
          "type": "text",
          "text": "欧姆定律电阻定律。串联并联电路的特点。电功电功率焦耳定律。闭合电路欧姆定律。"
        }
      ]
    },
    {
      "type": "element",
      "tag": "h2",
      "className": "section-title",
      "children": [
        {
          "type": "text",
          "text": "磁场"
        }
      ]
    },
    {
      "type": "element",
      "tag": "p",
      "children": [
        {
          "type": "text",
          "text": "磁感应强度安培力洛伦兹力。带电粒子在匀强磁场中的圆周运动。质谱仪和回旋加速器的原理。"
        }
      ]
    },
    {
      "type": "element",
      "tag": "h2",
      "className": "section-title",
      "children": [
        {
          "type": "text",
          "text": "电磁感应"
        }
      ]
    },
    {
      "type": "element",
      "tag": "p",
      "children": [
        {
          "type": "text",
          "text": "法拉第电磁感应定律E=n倍delta phi/delta t。楞次定律判断感应电流方向。自感现象和互感。"
        }
      ]
    }
  ],
  "sourceFiles": [
    "data/knowledge-pages.json"
  ]
}